pymodaq_plugin_manager/__init__.py
pymodaq_plugin_manager/compatibility_checker.py
pymodaq_plugin_manager/manager.py
pymodaq_plugin_manager/utils.py
pymodaq_plugin_manager/validate.py
pymodaq_plugin_manager/data/PluginList.json
pymodaq_plugin_manager/data/plugin_list.schema
pymodaq_plugin_manager-1.3.6.dist-info/METADATA
pymodaq_plugin_manager-1.3.6.dist-info/WHEEL
pymodaq_plugin_manager-1.3.6.dist-info/entry_points.txt
pymodaq_plugin_manager-1.3.6.dist-info/licenses/LICENSE
pymodaq_plugin_manager-1.3.6.dist-info/RECORD
