Metadata-Version: 2.4
Name: pymodaq_plugin_manager
Version: 1.3.6
Summary: Manager and interface to list, install or remove PyMoDAQ's plugins
Project-URL: Homepage, http://pymodaq.cnrs.fr
Project-URL: Source, https://github.com/PyMoDAQ/pymodaq_plugins_manager
Project-URL: Tracker, https://github.com/PyMoDAQ/pymodaq_plugins_manager/issues
Author-email: Sébastien Weber <sebastien.weber@cemes.fr>
License: The MIT License (MIT)
License-File: LICENSE
Classifier: Development Status :: 5 - Production/Stable
Classifier: Environment :: Other Environment
Classifier: Intended Audience :: Science/Research
Classifier: License :: OSI Approved :: MIT License
Classifier: Natural Language :: English
Classifier: Operating System :: OS Independent
Classifier: Programming Language :: Python :: 3.9
Classifier: Programming Language :: Python :: 3.10
Classifier: Programming Language :: Python :: 3.11
Classifier: Programming Language :: Python :: 3.12
Classifier: Topic :: Scientific/Engineering :: Human Machine Interfaces
Classifier: Topic :: Scientific/Engineering :: Visualization
Classifier: Topic :: Software Development :: Libraries :: Python Modules
Classifier: Topic :: Software Development :: User Interfaces
Requires-Python: >=3.9
Requires-Dist: chardet
Requires-Dist: distlib
Requires-Dist: jsonschema
Requires-Dist: lxml
Requires-Dist: packaging
Requires-Dist: pytablewriter
Requires-Dist: readme-renderer
Requires-Dist: requests
Requires-Dist: yawrap
